alacorderlite/__init__.py
alacorderlite/__main__.py
alacorderlite/alac.py
alacorderlite-78.2.1.dist-info/LICENSE
alacorderlite-78.2.1.dist-info/METADATA
alacorderlite-78.2.1.dist-info/WHEEL
alacorderlite-78.2.1.dist-info/top_level.txt
alacorderlite-78.2.1.dist-info/RECORD
