Metadata-Version: 2.1
Name: alacorderlite
Version: 78.2.1
Summary: Alacorder collects and processes case detail PDFs into data tables suitable for research purposes. Alacorder also generates compressed text archives from the source PDFs to speed future data collection from the same set of cases. Google Chrome required for direct access to case PDFs via query template (see /templates on GitHub).
Author-email: Sam Robson <sbrobson@crimson.ua.edu>
Classifier: Programming Language :: Python :: 3
Classifier: License :: OSI Approved :: MIT License
Classifier: Operating System :: OS Independent
Requires-Python: >=3.9
License-File: LICENSE
Requires-Dist: click
Requires-Dist: PySimpleGUI
Requires-Dist: pandas (==2.0.0rc0)
Requires-Dist: tqdm (>=4.65.0)
Requires-Dist: PyPDF2
Requires-Dist: selenium
Requires-Dist: openpyxl
